pytest_homeassistant_custom_component/__init__.py
pytest_homeassistant_custom_component/asyncio_legacy.py
pytest_homeassistant_custom_component/common.py
pytest_homeassistant_custom_component/const.py
pytest_homeassistant_custom_component/ignore_uncaught_exceptions.py
pytest_homeassistant_custom_component/patch_json.py
pytest_homeassistant_custom_component/patch_recorder.py
pytest_homeassistant_custom_component/patch_time.py
pytest_homeassistant_custom_component/plugins.py
pytest_homeassistant_custom_component/syrupy.py
pytest_homeassistant_custom_component/typing.py
pytest_homeassistant_custom_component/components/__init__.py
pytest_homeassistant_custom_component/components/diagnostics/__init__.py
pytest_homeassistant_custom_component/components/recorder/__init__.py
pytest_homeassistant_custom_component/components/recorder/common.py
pytest_homeassistant_custom_component/components/recorder/db_schema_0.py
pytest_homeassistant_custom_component/test_util/__init__.py
pytest_homeassistant_custom_component/test_util/aiohttp.py
pytest_homeassistant_custom_component/testing_config/__init__.py
pytest_homeassistant_custom_component/testing_config/custom_components/__init__.py
pytest_homeassistant_custom_component/testing_config/custom_components/test_constant_deprecation/__init__.py
pytest_homeassistant_custom_component-0.13.310.dist-info/licenses/LICENSE
pytest_homeassistant_custom_component-0.13.310.dist-info/licenses/LICENSE_HA_CORE.md
pytest_homeassistant_custom_component-0.13.310.dist-info/METADATA
pytest_homeassistant_custom_component-0.13.310.dist-info/WHEEL
pytest_homeassistant_custom_component-0.13.310.dist-info/entry_points.txt
pytest_homeassistant_custom_component-0.13.310.dist-info/top_level.txt
pytest_homeassistant_custom_component-0.13.310.dist-info/RECORD
