Metadata-Version: 2.4
Name: pytest-homeassistant-custom-component
Version: 0.13.310
Summary: Experimental package to automatically extract test plugins for Home Assistant custom components
Home-page: https://github.com/MatthewFlamm/pytest-homeassistant-custom-component
Author: Matthew Flamm
Author-email: matthewflamm0@gmail.com
License: MIT license
Classifier: Development Status :: 3 - Alpha
Classifier: Framework :: Pytest
Classifier: Intended Audience :: Developers
Classifier: License :: OSI Approved :: MIT License
Classifier: Programming Language :: Python
Classifier: Programming Language :: Python :: 3.13
Classifier: Topic :: Software Development :: Testing
Requires-Python: >=3.13
License-File: LICENSE
License-File: LICENSE_HA_CORE.md
Requires-Dist: sqlalchemy
Requires-Dist: coverage==7.10.6
Requires-Dist: freezegun==1.5.2
Requires-Dist: license-expression==30.4.3
Requires-Dist: mock-open==1.4.0
Requires-Dist: prek==0.2.28
Requires-Dist: pydantic==2.12.2
Requires-Dist: pylint-per-file-ignores==1.4.0
Requires-Dist: pipdeptree==2.26.1
Requires-Dist: pytest-asyncio==1.3.0
Requires-Dist: pytest-aiohttp==1.1.0
Requires-Dist: pytest-cov==7.0.0
Requires-Dist: pytest-freezer==0.4.9
Requires-Dist: pytest-github-actions-annotate-failures==0.3.0
Requires-Dist: pytest-socket==0.7.0
Requires-Dist: pytest-sugar==1.0.0
Requires-Dist: pytest-timeout==2.4.0
Requires-Dist: pytest-unordered==0.7.0
Requires-Dist: pytest-picked==0.5.1
Requires-Dist: pytest-xdist==3.8.0
Requires-Dist: pytest==9.0.0
Requires-Dist: requests-mock==1.12.1
Requires-Dist: respx==0.22.0
Requires-Dist: syrupy==5.0.0
Requires-Dist: tqdm==4.67.1
Requires-Dist: homeassistant==2026.2.0b1
Requires-Dist: SQLAlchemy==2.0.41
Requires-Dist: paho-mqtt==2.1.0
Requires-Dist: numpy==2.3.2
Dynamic: author
Dynamic: author-email
Dynamic: classifier
Dynamic: description
Dynamic: description-content-type
Dynamic: home-page
Dynamic: license
Dynamic: license-file
Dynamic: requires-dist
Dynamic: requires-python
Dynamic: summary
